{
  "schema_version": "v1",
  "record_type": "train_and_eval",
  "experiment_id": "dct_cnn_hemg_train_and_eval",
  "run_id": "dct_cnn_hemg",
  "date": "2026-04-14",
  "owner": "需手动填写",
  "stage": "improved",
  "tags": [
    "frequency",
    "dct",
    "frank2020",
    "hemg"
  ],
  "include_in_report": false,
  "include_in_ppt": false,
  "git_commit": "b5360983807f92cf144031942a995e19ebf65022",
  "script_path": "our_framwork/频谱图/train_dct.py",
  "command": "'our_framwork/频谱图/train_dct.py' --epochs 10 --save-every 5",
  "seed": 4210,
  "device": "mps",
  "purpose": "需手动填写",
  "hypothesis": "需手动填写",
  "compare_to": [
    "需手动填写"
  ],
  "data": {
    "train_data_root": "/Users/jiangyanze/MyCode/MyProject/Course Project/DDA4210/data/hemg_processed",
    "val_data_root": "/Users/jiangyanze/MyCode/MyProject/Course Project/DDA4210/data/hemg_processed",
    "test_data_root": "/Users/jiangyanze/MyCode/MyProject/Course Project/DDA4210/data/hemg_processed",
    "benchmark_data_root": "需手动填写",
    "train_split": "train",
    "val_split": "val",
    "test_split": "test",
    "bias_control": true,
    "train_size_per_class": "full",
    "input_resolution": 224,
    "save_format": "jpeg",
    "preprocess_note": "Resize(256) + CenterCrop(224), 像素归一化到 [-1,1], 逐通道 2D DCT (type-II, ortho) + log-scale"
  },
  "model": {
    "model_name": "dct_cnn",
    "method_family": "frequency_analysis",
    "backbone": "DCTClassifier (4-layer CNN on DCT coefficients)",
    "pretrained": false,
    "frozen_backbone": false,
    "forensic_branch": "dct_spectrum",
    "fusion_method": "none"
  },
  "training": {
    "enabled": true,
    "output_dir": "/Users/jiangyanze/MyCode/MyProject/Course Project/DDA4210/our_framwork/频谱图/output",
    "checkpoint_path": "/Users/jiangyanze/MyCode/MyProject/Course Project/DDA4210/our_framwork/频谱图/参数/best_dct.pt",
    "loss_fn": "CrossEntropyLoss",
    "optimizer": "AdamW",
    "lr": 0.001,
    "weight_decay": 0.0001,
    "batch_size": 64,
    "epochs": 10,
    "patience": 5,
    "best_epoch": 8,
    "train_loss": 0.45609525004348744,
    "val_metrics": {
      "accuracy": 0.7712657979176216,
      "auc": 0.8553586354775278,
      "f1": 0.7741351438732622,
      "loss": 0.48148571204697327
    },
    "in_domain_test_metrics": {
      "accuracy": 0.7658961430161745,
      "auc": 0.8496122148991739,
      "f1": 0.771053474223503,
      "loss": 0.48796761338021183
    }
  },
  "evaluations": [
    {
      "eval_id": "需手动填写",
      "enabled": true,
      "checkpoint_path": "our_framwork/频谱图/参数/best_dct.pt",
      "eval_type": "in_domain_test",
      "data_root": "data/hemg_processed",
      "split": "test",
      "perturbation": {
        "type": "none",
        "jpeg_quality": null,
        "resize_setting": null
      },
      "metrics": {
        "accuracy": 0.7658961430161745,
        "auc": 0.8496122148991739,
        "f1": 0.771053474223503,
        "loss": 0.48796761338021183
      },
      "num_samples": 15271,
      "skipped_files": [],
      "note": "自动记录：DCT-CNN 在 HEMG 标准测试集上的结果"
    }
  ],
  "summary": {
    "main_finding": "需手动填写",
    "failure_mode": "需手动填写",
    "is_abnormal": false,
    "next_action": "需手动填写",
    "report_sentence": "需手动填写"
  },
  "history": [
    {
      "epoch": 1,
      "train_loss": 0.600118048313941,
      "val_loss": 0.7571076984435493,
      "val_accuracy": 0.5885665640756991,
      "val_auc": 0.6903222816683415,
      "val_f1": 0.710554199106279
    },
    {
      "epoch": 2,
      "train_loss": 0.5661099850097111,
      "val_loss": 0.7139129973091753,
      "val_accuracy": 0.634143147141641,
      "val_auc": 0.744137923944228,
      "val_f1": 0.7251709380687688
    },
    {
      "epoch": 3,
      "train_loss": 0.5455914547585308,
      "val_loss": 0.5479266637942699,
      "val_accuracy": 0.7182240848667408,
      "val_auc": 0.8022072286464359,
      "val_f1": 0.7531409557684585
    },
    {
      "epoch": 4,
      "train_loss": 0.5301087307899548,
      "val_loss": 0.8690116296902082,
      "val_accuracy": 0.606640036670814,
      "val_auc": 0.7385709105671462,
      "val_f1": 0.7159139276424686
    },
    {
      "epoch": 5,
      "train_loss": 0.5163495081064783,
      "val_loss": 0.722292126704352,
      "val_accuracy": 0.5860127038176937,
      "val_auc": 0.7362517220456526,
      "val_f1": 0.6965245775729647
    },
    {
      "epoch": 6,
      "train_loss": 0.5009105270171663,
      "val_loss": 0.48258724462875924,
      "val_accuracy": 0.7692358064304892,
      "val_auc": 0.8496113452443781,
      "val_f1": 0.7827641474540747
    },
    {
      "epoch": 7,
      "train_loss": 0.48512392585313935,
      "val_loss": 0.5732159437126858,
      "val_accuracy": 0.7183550520594592,
      "val_auc": 0.8243703380690888,
      "val_f1": 0.7718907451604349
    },
    {
      "epoch": 8,
      "train_loss": 0.4726147679716327,
      "val_loss": 0.48148571204697327,
      "val_accuracy": 0.7712657979176216,
      "val_auc": 0.8553586354775278,
      "val_f1": 0.7741351438732622
    },
    {
      "epoch": 9,
      "train_loss": 0.462490320498423,
      "val_loss": 0.5179651970752805,
      "val_accuracy": 0.7456617117412089,
      "val_auc": 0.8487605473197428,
      "val_f1": 0.7886373530692207
    },
    {
      "epoch": 10,
      "train_loss": 0.45609525004348744,
      "val_loss": 0.8411513106265289,
      "val_accuracy": 0.6402986051993975,
      "val_auc": 0.7952293940978992,
      "val_f1": 0.5719629081274838
    }
  ]
}